ratsnlp/__init__.py
ratsnlp/nlpbook/__init__.py
ratsnlp/nlpbook/data_utils.py
ratsnlp/nlpbook/metrics.py
ratsnlp/nlpbook/trainer.py
ratsnlp/nlpbook/utils.py
ratsnlp/nlpbook/classification/__init__.py
ratsnlp/nlpbook/classification/arguments.py
ratsnlp/nlpbook/classification/corpus.py
ratsnlp/nlpbook/classification/deploy.py
ratsnlp/nlpbook/classification/index.html
ratsnlp/nlpbook/classification/task.py
ratsnlp/nlpbook/generation/__init__.py
ratsnlp/nlpbook/generation/arguments.py
ratsnlp/nlpbook/generation/corpus.py
ratsnlp/nlpbook/generation/deploy.py
ratsnlp/nlpbook/generation/index.html
ratsnlp/nlpbook/generation/task.py
ratsnlp/nlpbook/ner/__init__.py
ratsnlp/nlpbook/ner/arguments.py
ratsnlp/nlpbook/ner/corpus.py
ratsnlp/nlpbook/ner/deploy.py
ratsnlp/nlpbook/ner/index.html
ratsnlp/nlpbook/ner/task.py
ratsnlp/nlpbook/paircls/__init__.py
ratsnlp/nlpbook/paircls/corpus.py
ratsnlp/nlpbook/paircls/deploy.py
ratsnlp/nlpbook/paircls/index.html
ratsnlp/nlpbook/qa/__init__.py
ratsnlp/nlpbook/qa/arguments.py
ratsnlp/nlpbook/qa/corpus.py
ratsnlp/nlpbook/qa/deploy.py
ratsnlp/nlpbook/qa/index.html
ratsnlp/nlpbook/qa/task.py
ratsnlp-1.0.53.dist-info/LICENSE
ratsnlp-1.0.53.dist-info/METADATA
ratsnlp-1.0.53.dist-info/WHEEL
ratsnlp-1.0.53.dist-info/top_level.txt
ratsnlp-1.0.53.dist-info/RECORD
