Metadata-Version: 2.1
Name: ratsnlp
Version: 1.0.53
Summary: tools for Natural Language Processing
Home-page: https://github.com/ratsgo/ratsnlp
Author: ratsgo
Author-email: ratsgo@naver.com
License: MIT
Classifier: Programming Language :: Python :: 3.7
Classifier: License :: OSI Approved :: MIT License
Classifier: Operating System :: OS Independent
License-File: LICENSE
Requires-Dist: pytorch-lightning (==1.6.1)
Requires-Dist: transformers (==4.28.1)
Requires-Dist: Korpora (>=0.2.0)
Requires-Dist: flask (>=1.1.4)
Requires-Dist: flask-ngrok (>=0.0.25)
Requires-Dist: flask-cors (>=3.0.10)
